mt3_audio2midi/__init__.py
mt3_audio2midi/py.typed
mt3_audio2midi/airio/core.py
mt3_audio2midi/airio/pygrain.py
mt3_audio2midi/airio/pygrain_common.py
mt3_audio2midi/airio/version.py
mt3_audio2midi/airio/_src/core/data_sources.py
mt3_audio2midi/airio/_src/core/dataset_iterators.py
mt3_audio2midi/airio/_src/core/dataset_providers.py
mt3_audio2midi/airio/_src/core/preprocessors.py
mt3_audio2midi/airio/_src/core/test_utils.py
mt3_audio2midi/airio/_src/core/tokenizer.py
mt3_audio2midi/airio/_src/core/vocabularies.py
mt3_audio2midi/airio/_src/pygrain/data_sources.py
mt3_audio2midi/airio/_src/pygrain/dataset_iterators.py
mt3_audio2midi/airio/_src/pygrain/dataset_providers.py
mt3_audio2midi/airio/_src/pygrain/lazy_dataset_transforms.py
mt3_audio2midi/airio/_src/pygrain/preprocessors.py
mt3_audio2midi/airio/_src/pygrain/tokenizer.py
mt3_audio2midi/airio/_src/pygrain/vocabularies.py
mt3_audio2midi/airio/_src/pygrain/common/constants.py
mt3_audio2midi/airio/_src/pygrain/common/feature_converters.py
mt3_audio2midi/airio/_src/pygrain/common/packing.py
mt3_audio2midi/airio/_src/pygrain/common/preprocessors.py
mt3_audio2midi/airio/_src/pygrain/common/span_corruption.py
mt3_audio2midi/gin/eval.gin
mt3_audio2midi/gin/infer.gin
mt3_audio2midi/gin/ismir2021.gin
mt3_audio2midi/gin/local_tiny.gin
mt3_audio2midi/gin/model.gin
mt3_audio2midi/gin/mt3.gin
mt3_audio2midi/gin/train.gin
mt3_audio2midi/gin/ismir2022/base.gin
mt3_audio2midi/gin/ismir2022/finetune.gin
mt3_audio2midi/gin/ismir2022/pretrain.gin
mt3_audio2midi/gin/ismir2022/small.gin
mt3_audio2midi/jestimator/__init__.py
mt3_audio2midi/jestimator/amos.py
mt3_audio2midi/jestimator/amos_helper.py
mt3_audio2midi/jestimator/checkpoint_utils.py
mt3_audio2midi/jestimator/data_utils.py
mt3_audio2midi/jestimator/estimator.py
mt3_audio2midi/jestimator/modeling.py
mt3_audio2midi/jestimator/states.py
mt3_audio2midi/jestimator/data/pipeline_lm.py
mt3_audio2midi/jestimator/data/pipeline_rec.py
mt3_audio2midi/jestimator/data/pipeline_seqio.py
mt3_audio2midi-0.2.0.dist-info/METADATA
mt3_audio2midi-0.2.0.dist-info/WHEEL
mt3_audio2midi-0.2.0.dist-info/RECORD
