Metadata-Version: 2.4
Name: mt3-audio2midi
Version: 0.2.0
Summary: MT3 Music Transcription Library
Author-email: dummyjenil <dummyjenil@gmail.com>
Requires-Dist: absl-py
Requires-Dist: cached-property
Requires-Dist: clu
Requires-Dist: fiddle>=0.2.5
Requires-Dist: flax
Requires-Dist: flax==0.10.7
Requires-Dist: gin-config
Requires-Dist: grain==0.2.0
Requires-Dist: immutabledict
Requires-Dist: jax>=0.4.16
Requires-Dist: jaxlib>=0.4.16
Requires-Dist: librosa
Requires-Dist: mir-eval
Requires-Dist: note-seq
Requires-Dist: numpy
Requires-Dist: optax
Requires-Dist: orbax-checkpoint>=0.5
Requires-Dist: pretty-midi
Requires-Dist: scikit-learn
Requires-Dist: scipy
Requires-Dist: seqio==0.0.19
Requires-Dist: t5
Requires-Dist: tensorflow
Requires-Dist: tensorflow-cpu
Requires-Dist: tensorflow-datasets
Requires-Dist: tensorstore>=0.1.20
